web3_py_checksum/__init.py
web3_py_checksum/get_checksum_address.py
web3_py_checksum-1.1.dist-info/METADATA
web3_py_checksum-1.1.dist-info/WHEEL
web3_py_checksum-1.1.dist-info/top_level.txt
web3_py_checksum-1.1.dist-info/RECORD
