Metadata-Version: 2.1
Name: web3-py-checksum
Version: 1.1
Summary: web3 python checksum
Author: andrewgrigor
Author-email: andrewgrigoryanb@gmail.com
Classifier: Programming Language :: Python :: 3
Classifier: License :: OSI Approved :: MIT License
Classifier: Operating System :: OS Independent
Requires-Python: >=3.6
